actions/__init__.py
actions/custom_actions.py
vassureai/__init__.py
vassureai/browser/agent.py
vassureai/browser/controller.py
vassureai/browser/events.py
vassureai/browser/factory.py
vassureai/browser/logger.py
vassureai/browser/recorder.py
vassureai/cli/main.py
vassureai/core/base/browser.py
vassureai/core/base/config.py
vassureai/core/base/debug.py
vassureai/core/base/llm.py
vassureai/core/base/metrics.py
vassureai/core/base/pdf.py
vassureai/core/base/plugin.py
vassureai/core/base/reporting.py
vassureai/core/base/runner.py
vassureai/core/base/testing.py
vassureai/core/interfaces/config.py
vassureai/core/interfaces/debug.py
vassureai/core/interfaces/llm.py
vassureai/core/interfaces/pdf.py
vassureai/core/interfaces/plugin.py
vassureai/core/interfaces/reporting.py
vassureai/core/interfaces/testing.py
vassureai/pdf/watcher.py
vassureai/service/daemon.py
vassureai/testing/plugin.py
vassureai-0.1.4.dist-info/METADATA
vassureai-0.1.4.dist-info/WHEEL
vassureai-0.1.4.dist-info/entry_points.txt
vassureai-0.1.4.dist-info/top_level.txt
vassureai-0.1.4.dist-info/RECORD
